src/LambdaFunction.py
src/S3.py
src/Zip.py
src/__init__.py
src/configManager.py
src/main.py
deploy_lambda_functions-1.0.9.dist-info/METADATA
deploy_lambda_functions-1.0.9.dist-info/WHEEL
deploy_lambda_functions-1.0.9.dist-info/entry_points.txt
deploy_lambda_functions-1.0.9.dist-info/top_level.txt
deploy_lambda_functions-1.0.9.dist-info/RECORD
