Metadata-Version: 2.1
Name: deploy-lambda-functions
Version: 1.0.9
Summary: Script to deploy lambda functions to AWS
Home-page: https://github.com/redaptiveinc/deploy-lambda-functions
Author: Mariano Gimenez
Author-email: mariano.gimenez@agileengine.com
License: unlicense
Platform: UNKNOWN
Requires-Dist: python-dotenv (==0.10.3)
Requires-Dist: boto3 (==1.17.24)
Requires-Dist: botocore (==1.20.24)
